envoy/distribution/distrotest/__init__.py
envoy/distribution/distrotest/distrotest.py
envoy/distribution/distrotest/distrotest.sh
envoy/distribution/distrotest/distrotest.yaml
envoy/distribution/distrotest/py.typed
envoy.distribution.distrotest-0.0.12.dist-info/METADATA
envoy.distribution.distrotest-0.0.12.dist-info/WHEEL
envoy.distribution.distrotest-0.0.12.dist-info/namespace_packages.txt
envoy.distribution.distrotest-0.0.12.dist-info/top_level.txt
envoy.distribution.distrotest-0.0.12.dist-info/RECORD
