Metadata-Version: 2.1
Name: envoy.distribution.distrotest
Version: 0.0.12
Summary: "Lib for testing packages with distributions in Envoy proxy's CI"
Home-page: https://github.com/envoyproxy/toolshed/tree/main/envoy.distribution.distrotest
Author: Ryan Northey
Author-email: ryan@synca.io
Maintainer: Ryan Northey
Maintainer-email: ryan@synca.io
License: Apache Software License 2.0
Requires-Python: >=3.11.0
Requires-Dist: aio.run.checker (>=0.5.8)
Requires-Dist: envoy.base.utils (>=0.5.7)
Requires-Dist: envoy.docker.utils (>=0.0.2)
